{
    "danceability": 0.424,
    "energy": 0.0143,
    "key": 5,
    "loudness": -26.003,
    "mode": 0,
    "speechiness": 0.0456,
    "acousticness": 0.993,
    "instrumentalness": 0.91,
    "liveness": 0.0705,
    "valence": 0.0685,
    "tempo": 128.332,
    "type": "audio_features",
    "id": "08QGTXVi5hvEmKtZxrn4Ng",
    "uri": "spotify:track:08QGTXVi5hvEmKtZxrn4Ng",
    "track_href": "https://api.spotify.com/v1/tracks/08QGTXVi5hvEmKtZxrn4Ng",
    "analysis_url": "https://api.spotify.com/v1/audio-analysis/08QGTXVi5hvEmKtZxrn4Ng",
    "duration_ms": 368720,
    "time_signature": 4
}