{
    "danceability": 0.719,
    "energy": 0.75,
    "key": 8,
    "loudness": -6.365,
    "mode": 1,
    "speechiness": 0.0637,
    "acousticness": 0.229,
    "instrumentalness": 0.853,
    "liveness": 0.101,
    "valence": 0.476,
    "tempo": 140.059,
    "type": "audio_features",
    "id": "0hkHNlWZYBCOc4BL8jmuuF",
    "uri": "spotify:track:0hkHNlWZYBCOc4BL8jmuuF",
    "track_href": "https://api.spotify.com/v1/tracks/0hkHNlWZYBCOc4BL8jmuuF",
    "analysis_url": "https://api.spotify.com/v1/audio-analysis/0hkHNlWZYBCOc4BL8jmuuF",
    "duration_ms": 134629,
    "time_signature": 3
}