{
    "danceability": 0.534,
    "energy": 0.887,
    "key": 0,
    "loudness": -3.777,
    "mode": 1,
    "speechiness": 0.0345,
    "acousticness": 0.0768,
    "instrumentalness": 9.93e-05,
    "liveness": 0.325,
    "valence": 0.72,
    "tempo": 122.494,
    "type": "audio_features",
    "id": "0J6mQxEZnlRt9ymzFntA6z",
    "uri": "spotify:track:0J6mQxEZnlRt9ymzFntA6z",
    "track_href": "https://api.spotify.com/v1/tracks/0J6mQxEZnlRt9ymzFntA6z",
    "analysis_url": "https://api.spotify.com/v1/audio-analysis/0J6mQxEZnlRt9ymzFntA6z",
    "duration_ms": 249293,
    "time_signature": 4
}