{
    "danceability": 0.749,
    "energy": 0.476,
    "key": 11,
    "loudness": -11.147,
    "mode": 0,
    "speechiness": 0.507,
    "acousticness": 0.579,
    "instrumentalness": 0,
    "liveness": 0.1,
    "valence": 0.534,
    "tempo": 71.937,
    "type": "audio_features",
    "id": "0JaVdpmiex2EP7bBzyKVTa",
    "uri": "spotify:track:0JaVdpmiex2EP7bBzyKVTa",
    "track_href": "https://api.spotify.com/v1/tracks/0JaVdpmiex2EP7bBzyKVTa",
    "analysis_url": "https://api.spotify.com/v1/audio-analysis/0JaVdpmiex2EP7bBzyKVTa",
    "duration_ms": 188189,
    "time_signature": 4
}