{
    "danceability": 0.778,
    "energy": 0.399,
    "key": 7,
    "loudness": -8.139,
    "mode": 0,
    "speechiness": 0.0356,
    "acousticness": 0.0581,
    "instrumentalness": 0.908,
    "liveness": 0.0582,
    "valence": 0.224,
    "tempo": 124.003,
    "type": "audio_features",
    "id": "0nM9bf0YOtYcBeUtwEp68x",
    "uri": "spotify:track:0nM9bf0YOtYcBeUtwEp68x",
    "track_href": "https://api.spotify.com/v1/tracks/0nM9bf0YOtYcBeUtwEp68x",
    "analysis_url": "https://api.spotify.com/v1/audio-analysis/0nM9bf0YOtYcBeUtwEp68x",
    "duration_ms": 343065,
    "time_signature": 4
}