{
    "danceability": 0.197,
    "energy": 0.786,
    "key": 2,
    "loudness": -7.497,
    "mode": 1,
    "speechiness": 0.049,
    "acousticness": 0.00134,
    "instrumentalness": 0.819,
    "liveness": 0.23,
    "valence": 0.457,
    "tempo": 113.132,
    "type": "audio_features",
    "id": "0R2xy4cVDKxCs8DNSFrqJu",
    "uri": "spotify:track:0R2xy4cVDKxCs8DNSFrqJu",
    "track_href": "https://api.spotify.com/v1/tracks/0R2xy4cVDKxCs8DNSFrqJu",
    "analysis_url": "https://api.spotify.com/v1/audio-analysis/0R2xy4cVDKxCs8DNSFrqJu",
    "duration_ms": 237933,
    "time_signature": 4
}