{
    "danceability": 0.552,
    "energy": 0.246,
    "key": 9,
    "loudness": -15.839,
    "mode": 1,
    "speechiness": 0.0369,
    "acousticness": 0.333,
    "instrumentalness": 0.917,
    "liveness": 0.0932,
    "valence": 0.0353,
    "tempo": 119.971,
    "type": "audio_features",
    "id": "0tvUuLOyOguXLGmbNgg0qI",
    "uri": "spotify:track:0tvUuLOyOguXLGmbNgg0qI",
    "track_href": "https://api.spotify.com/v1/tracks/0tvUuLOyOguXLGmbNgg0qI",
    "analysis_url": "https://api.spotify.com/v1/audio-analysis/0tvUuLOyOguXLGmbNgg0qI",
    "duration_ms": 134221,
    "time_signature": 4
}