{
    "danceability": 0.628,
    "energy": 0.917,
    "key": 8,
    "loudness": -7.623,
    "mode": 1,
    "speechiness": 0.0428,
    "acousticness": 8.43e-05,
    "instrumentalness": 0.213,
    "liveness": 0.179,
    "valence": 0.261,
    "tempo": 122.976,
    "type": "audio_features",
    "id": "0WAgwdyjTwx2TT55W8z8lu",
    "uri": "spotify:track:0WAgwdyjTwx2TT55W8z8lu",
    "track_href": "https://api.spotify.com/v1/tracks/0WAgwdyjTwx2TT55W8z8lu",
    "analysis_url": "https://api.spotify.com/v1/audio-analysis/0WAgwdyjTwx2TT55W8z8lu",
    "duration_ms": 159250,
    "time_signature": 4
}