{
    "danceability": 0.724,
    "energy": 0.482,
    "key": 9,
    "loudness": -12.392,
    "mode": 1,
    "speechiness": 0.0301,
    "acousticness": 0.0335,
    "instrumentalness": 8.11e-06,
    "liveness": 0.111,
    "valence": 0.929,
    "tempo": 123.268,
    "type": "audio_features",
    "id": "13E83DbMKsGAhVokHDMzTQ",
    "uri": "spotify:track:13E83DbMKsGAhVokHDMzTQ",
    "track_href": "https://api.spotify.com/v1/tracks/13E83DbMKsGAhVokHDMzTQ",
    "analysis_url": "https://api.spotify.com/v1/audio-analysis/13E83DbMKsGAhVokHDMzTQ",
    "duration_ms": 182453,
    "time_signature": 4
}