{
    "danceability": 0.807,
    "energy": 0.701,
    "key": 7,
    "loudness": -9.425,
    "mode": 1,
    "speechiness": 0.0495,
    "acousticness": 6.76e-05,
    "instrumentalness": 0.909,
    "liveness": 0.127,
    "valence": 0.931,
    "tempo": 124.03,
    "type": "audio_features",
    "id": "17urFGvNhZAZXZt6OTZ8Mi",
    "uri": "spotify:track:17urFGvNhZAZXZt6OTZ8Mi",
    "track_href": "https://api.spotify.com/v1/tracks/17urFGvNhZAZXZt6OTZ8Mi",
    "analysis_url": "https://api.spotify.com/v1/audio-analysis/17urFGvNhZAZXZt6OTZ8Mi",
    "duration_ms": 372640,
    "time_signature": 4
}