{
    "danceability": 0.481,
    "energy": 0.491,
    "key": 11,
    "loudness": -9.2,
    "mode": 1,
    "speechiness": 0.03,
    "acousticness": 0.682,
    "instrumentalness": 0.0563,
    "liveness": 0.121,
    "valence": 0.621,
    "tempo": 154.879,
    "type": "audio_features",
    "id": "1bdp1CY6vfKPESMCa2NI1M",
    "uri": "spotify:track:1bdp1CY6vfKPESMCa2NI1M",
    "track_href": "https://api.spotify.com/v1/tracks/1bdp1CY6vfKPESMCa2NI1M",
    "analysis_url": "https://api.spotify.com/v1/audio-analysis/1bdp1CY6vfKPESMCa2NI1M",
    "duration_ms": 281787,
    "time_signature": 4
}