{
    "danceability": 0.0924,
    "energy": 0.0344,
    "key": 8,
    "loudness": -32.943,
    "mode": 1,
    "speechiness": 0.0409,
    "acousticness": 0.404,
    "instrumentalness": 0.906,
    "liveness": 0.294,
    "valence": 0.0361,
    "tempo": 65.668,
    "type": "audio_features",
    "id": "1BIJdGnfaDbN1oWPVOFAzV",
    "uri": "spotify:track:1BIJdGnfaDbN1oWPVOFAzV",
    "track_href": "https://api.spotify.com/v1/tracks/1BIJdGnfaDbN1oWPVOFAzV",
    "analysis_url": "https://api.spotify.com/v1/audio-analysis/1BIJdGnfaDbN1oWPVOFAzV",
    "duration_ms": 468853,
    "time_signature": 3
}