{
    "danceability": 0.586,
    "energy": 0.7,
    "key": 0,
    "loudness": -9.558,
    "mode": 1,
    "speechiness": 0.0363,
    "acousticness": 0.0589,
    "instrumentalness": 0.00125,
    "liveness": 0.0318,
    "valence": 0.897,
    "tempo": 147.245,
    "type": "audio_features",
    "id": "1HOMkjp0nHMaTnfAkslCQj",
    "uri": "spotify:track:1HOMkjp0nHMaTnfAkslCQj",
    "track_href": "https://api.spotify.com/v1/tracks/1HOMkjp0nHMaTnfAkslCQj",
    "analysis_url": "https://api.spotify.com/v1/audio-analysis/1HOMkjp0nHMaTnfAkslCQj",
    "duration_ms": 295400,
    "time_signature": 4
}