{
    "danceability": 0.651,
    "energy": 0.776,
    "key": 9,
    "loudness": -3.91,
    "mode": 1,
    "speechiness": 0.0424,
    "acousticness": 0.211,
    "instrumentalness": 0,
    "liveness": 0.316,
    "valence": 0.59,
    "tempo": 100.046,
    "type": "audio_features",
    "id": "1k8Licv2jaRTbRtAbJZ3In",
    "uri": "spotify:track:1k8Licv2jaRTbRtAbJZ3In",
    "track_href": "https://api.spotify.com/v1/tracks/1k8Licv2jaRTbRtAbJZ3In",
    "analysis_url": "https://api.spotify.com/v1/audio-analysis/1k8Licv2jaRTbRtAbJZ3In",
    "duration_ms": 174733,
    "time_signature": 4
}