{
    "danceability": 0.611,
    "energy": 0.556,
    "key": 9,
    "loudness": -12.865,
    "mode": 1,
    "speechiness": 0.0277,
    "acousticness": 0.248,
    "instrumentalness": 0.000746,
    "liveness": 0.251,
    "valence": 0.793,
    "tempo": 98.163,
    "type": "audio_features",
    "id": "1Lfe5FENwSucYTrnrjKUPp",
    "uri": "spotify:track:1Lfe5FENwSucYTrnrjKUPp",
    "track_href": "https://api.spotify.com/v1/tracks/1Lfe5FENwSucYTrnrjKUPp",
    "analysis_url": "https://api.spotify.com/v1/audio-analysis/1Lfe5FENwSucYTrnrjKUPp",
    "duration_ms": 149013,
    "time_signature": 4
}