{
    "danceability": 0.697,
    "energy": 0.467,
    "key": 1,
    "loudness": -9.142,
    "mode": 1,
    "speechiness": 0.169,
    "acousticness": 0.465,
    "instrumentalness": 0.91,
    "liveness": 0.139,
    "valence": 0.311,
    "tempo": 168.053,
    "type": "audio_features",
    "id": "1V5FImeKciMqeTzqUwsFfL",
    "uri": "spotify:track:1V5FImeKciMqeTzqUwsFfL",
    "track_href": "https://api.spotify.com/v1/tracks/1V5FImeKciMqeTzqUwsFfL",
    "analysis_url": "https://api.spotify.com/v1/audio-analysis/1V5FImeKciMqeTzqUwsFfL",
    "duration_ms": 164167,
    "time_signature": 5
}