{
    "danceability": 0.624,
    "energy": 0.857,
    "key": 0,
    "loudness": -4.444,
    "mode": 1,
    "speechiness": 0.0585,
    "acousticness": 0.00185,
    "instrumentalness": 0.00358,
    "liveness": 0.245,
    "valence": 0.435,
    "tempo": 104.977,
    "type": "audio_features",
    "id": "22sZ8JkpfLH5a2nH05Wk8x",
    "uri": "spotify:track:22sZ8JkpfLH5a2nH05Wk8x",
    "track_href": "https://api.spotify.com/v1/tracks/22sZ8JkpfLH5a2nH05Wk8x",
    "analysis_url": "https://api.spotify.com/v1/audio-analysis/22sZ8JkpfLH5a2nH05Wk8x",
    "duration_ms": 200880,
    "time_signature": 4
}