{
    "danceability": 0.439,
    "energy": 0.694,
    "key": 3,
    "loudness": -6.249,
    "mode": 0,
    "speechiness": 0.0391,
    "acousticness": 0.000815,
    "instrumentalness": 0.0525,
    "liveness": 0.117,
    "valence": 0.557,
    "tempo": 91.916,
    "type": "audio_features",
    "id": "2ix6bfJQw8SK9aDcebJgT3",
    "uri": "spotify:track:2ix6bfJQw8SK9aDcebJgT3",
    "track_href": "https://api.spotify.com/v1/tracks/2ix6bfJQw8SK9aDcebJgT3",
    "analysis_url": "https://api.spotify.com/v1/audio-analysis/2ix6bfJQw8SK9aDcebJgT3",
    "duration_ms": 262737,
    "time_signature": 4
}