{
    "danceability": 0.812,
    "energy": 0.588,
    "key": 5,
    "loudness": -8.918,
    "mode": 0,
    "speechiness": 0.19,
    "acousticness": 0.335,
    "instrumentalness": 2.31e-06,
    "liveness": 0.346,
    "valence": 0.673,
    "tempo": 112.996,
    "type": "audio_features",
    "id": "2OLD64kN8JzvNn3Aar7O26",
    "uri": "spotify:track:2OLD64kN8JzvNn3Aar7O26",
    "track_href": "https://api.spotify.com/v1/tracks/2OLD64kN8JzvNn3Aar7O26",
    "analysis_url": "https://api.spotify.com/v1/audio-analysis/2OLD64kN8JzvNn3Aar7O26",
    "duration_ms": 192447,
    "time_signature": 4
}