{
    "danceability": 0.515,
    "energy": 0.43,
    "key": 2,
    "loudness": -10.912,
    "mode": 1,
    "speechiness": 0.25,
    "acousticness": 0.81,
    "instrumentalness": 0.0069,
    "liveness": 0.126,
    "valence": 0.624,
    "tempo": 165.893,
    "type": "audio_features",
    "id": "2Q7j9wJk8DomZhKckPeHdy",
    "uri": "spotify:track:2Q7j9wJk8DomZhKckPeHdy",
    "track_href": "https://api.spotify.com/v1/tracks/2Q7j9wJk8DomZhKckPeHdy",
    "analysis_url": "https://api.spotify.com/v1/audio-analysis/2Q7j9wJk8DomZhKckPeHdy",
    "duration_ms": 219000,
    "time_signature": 4
}