{
    "danceability": 0.172,
    "energy": 0.987,
    "key": 7,
    "loudness": -6.045,
    "mode": 1,
    "speechiness": 0.182,
    "acousticness": 4.74e-05,
    "instrumentalness": 0.196,
    "liveness": 0.133,
    "valence": 0.0411,
    "tempo": 148.51,
    "type": "audio_features",
    "id": "2RLUwWWHqUzN4jA0qxigcI",
    "uri": "spotify:track:2RLUwWWHqUzN4jA0qxigcI",
    "track_href": "https://api.spotify.com/v1/tracks/2RLUwWWHqUzN4jA0qxigcI",
    "analysis_url": "https://api.spotify.com/v1/audio-analysis/2RLUwWWHqUzN4jA0qxigcI",
    "duration_ms": 663747,
    "time_signature": 4
}