{
    "danceability": 0.407,
    "energy": 0.926,
    "key": 9,
    "loudness": -4.463,
    "mode": 1,
    "speechiness": 0.0725,
    "acousticness": 0.00708,
    "instrumentalness": 0.896,
    "liveness": 0.109,
    "valence": 0.351,
    "tempo": 166.421,
    "type": "audio_features",
    "id": "2ucburMItP9zTPcMzcVl59",
    "uri": "spotify:track:2ucburMItP9zTPcMzcVl59",
    "track_href": "https://api.spotify.com/v1/tracks/2ucburMItP9zTPcMzcVl59",
    "analysis_url": "https://api.spotify.com/v1/audio-analysis/2ucburMItP9zTPcMzcVl59",
    "duration_ms": 291740,
    "time_signature": 4
}