{
    "danceability": 0.529,
    "energy": 0.116,
    "key": 4,
    "loudness": -13.636,
    "mode": 1,
    "speechiness": 0.0348,
    "acousticness": 0.935,
    "instrumentalness": 3.63e-05,
    "liveness": 0.231,
    "valence": 0.228,
    "tempo": 118.992,
    "type": "audio_features",
    "id": "2vp9MxUintbPqLJ8GmB1iZ",
    "uri": "spotify:track:2vp9MxUintbPqLJ8GmB1iZ",
    "track_href": "https://api.spotify.com/v1/tracks/2vp9MxUintbPqLJ8GmB1iZ",
    "analysis_url": "https://api.spotify.com/v1/audio-analysis/2vp9MxUintbPqLJ8GmB1iZ",
    "duration_ms": 242133,
    "time_signature": 3
}