{
    "danceability": 0.506,
    "energy": 0.0461,
    "key": 7,
    "loudness": -27.316,
    "mode": 0,
    "speechiness": 0.0702,
    "acousticness": 0.995,
    "instrumentalness": 0.962,
    "liveness": 0.11,
    "valence": 0.322,
    "tempo": 132.436,
    "type": "audio_features",
    "id": "2XUDxWhpULyCwZ6tSyAULr",
    "uri": "spotify:track:2XUDxWhpULyCwZ6tSyAULr",
    "track_href": "https://api.spotify.com/v1/tracks/2XUDxWhpULyCwZ6tSyAULr",
    "analysis_url": "https://api.spotify.com/v1/audio-analysis/2XUDxWhpULyCwZ6tSyAULr",
    "duration_ms": 134722,
    "time_signature": 4
}