{
    "danceability": 0.693,
    "energy": 0.827,
    "key": 10,
    "loudness": -6.437,
    "mode": 0,
    "speechiness": 0.0483,
    "acousticness": 0.0114,
    "instrumentalness": 0.189,
    "liveness": 0.32,
    "valence": 0.906,
    "tempo": 103.087,
    "type": "audio_features",
    "id": "2yTswsiLkNGzzzX54WroNS",
    "uri": "spotify:track:2yTswsiLkNGzzzX54WroNS",
    "track_href": "https://api.spotify.com/v1/tracks/2yTswsiLkNGzzzX54WroNS",
    "analysis_url": "https://api.spotify.com/v1/audio-analysis/2yTswsiLkNGzzzX54WroNS",
    "duration_ms": 281680,
    "time_signature": 4
}