{
    "danceability": 0.366,
    "energy": 0.681,
    "key": 7,
    "loudness": -8.468,
    "mode": 1,
    "speechiness": 0.0672,
    "acousticness": 0.516,
    "instrumentalness": 0,
    "liveness": 0.303,
    "valence": 0.86,
    "tempo": 169.346,
    "type": "audio_features",
    "id": "30txFxKhnMJqUXz0xx0x39",
    "uri": "spotify:track:30txFxKhnMJqUXz0xx0x39",
    "track_href": "https://api.spotify.com/v1/tracks/30txFxKhnMJqUXz0xx0x39",
    "analysis_url": "https://api.spotify.com/v1/audio-analysis/30txFxKhnMJqUXz0xx0x39",
    "duration_ms": 167227,
    "time_signature": 4
}