{
    "danceability": 0.552,
    "energy": 0.479,
    "key": 2,
    "loudness": -15.634,
    "mode": 0,
    "speechiness": 0.0591,
    "acousticness": 0.663,
    "instrumentalness": 0.867,
    "liveness": 0.14,
    "valence": 0.485,
    "tempo": 117.467,
    "type": "audio_features",
    "id": "32wlGWGlQ2KfNb7bn3nvzI",
    "uri": "spotify:track:32wlGWGlQ2KfNb7bn3nvzI",
    "track_href": "https://api.spotify.com/v1/tracks/32wlGWGlQ2KfNb7bn3nvzI",
    "analysis_url": "https://api.spotify.com/v1/audio-analysis/32wlGWGlQ2KfNb7bn3nvzI",
    "duration_ms": 308134,
    "time_signature": 4
}