{
    "danceability": 0.168,
    "energy": 0.23,
    "key": 7,
    "loudness": -17.991,
    "mode": 0,
    "speechiness": 0.0363,
    "acousticness": 0.968,
    "instrumentalness": 0.887,
    "liveness": 0.337,
    "valence": 0.0393,
    "tempo": 130.06,
    "type": "audio_features",
    "id": "343ddQVZOlgpQ4FWiSwMHP",
    "uri": "spotify:track:343ddQVZOlgpQ4FWiSwMHP",
    "track_href": "https://api.spotify.com/v1/tracks/343ddQVZOlgpQ4FWiSwMHP",
    "analysis_url": "https://api.spotify.com/v1/audio-analysis/343ddQVZOlgpQ4FWiSwMHP",
    "duration_ms": 202747,
    "time_signature": 4
}