{
    "danceability": 0.64,
    "energy": 0.582,
    "key": 1,
    "loudness": -9.529,
    "mode": 1,
    "speechiness": 0.041,
    "acousticness": 0.716,
    "instrumentalness": 0.00117,
    "liveness": 0.328,
    "valence": 0.085,
    "tempo": 100.024,
    "type": "audio_features",
    "id": "3i9fMFpVYB7FKmy9NCuzwS",
    "uri": "spotify:track:3i9fMFpVYB7FKmy9NCuzwS",
    "track_href": "https://api.spotify.com/v1/tracks/3i9fMFpVYB7FKmy9NCuzwS",
    "analysis_url": "https://api.spotify.com/v1/audio-analysis/3i9fMFpVYB7FKmy9NCuzwS",
    "duration_ms": 213250,
    "time_signature": 4
}