{
    "danceability": 0.471,
    "energy": 0.328,
    "key": 7,
    "loudness": -13.049,
    "mode": 1,
    "speechiness": 0.0268,
    "acousticness": 0.287,
    "instrumentalness": 0.00218,
    "liveness": 0.0833,
    "valence": 0.537,
    "tempo": 129.978,
    "type": "audio_features",
    "id": "3JeSmJwvbQkIqcZ0LM46wm",
    "uri": "spotify:track:3JeSmJwvbQkIqcZ0LM46wm",
    "track_href": "https://api.spotify.com/v1/tracks/3JeSmJwvbQkIqcZ0LM46wm",
    "analysis_url": "https://api.spotify.com/v1/audio-analysis/3JeSmJwvbQkIqcZ0LM46wm",
    "duration_ms": 232867,
    "time_signature": 4
}