{
    "danceability": 0.456,
    "energy": 0.772,
    "key": 9,
    "loudness": -14.54,
    "mode": 0,
    "speechiness": 0.099,
    "acousticness": 0.0756,
    "instrumentalness": 0.00097,
    "liveness": 0.118,
    "valence": 0.43,
    "tempo": 78.214,
    "type": "audio_features",
    "id": "3TLjvoo96RxZlg9iBOi8Jb",
    "uri": "spotify:track:3TLjvoo96RxZlg9iBOi8Jb",
    "track_href": "https://api.spotify.com/v1/tracks/3TLjvoo96RxZlg9iBOi8Jb",
    "analysis_url": "https://api.spotify.com/v1/audio-analysis/3TLjvoo96RxZlg9iBOi8Jb",
    "duration_ms": 151733,
    "time_signature": 4
}