{
    "danceability": 0.402,
    "energy": 0.698,
    "key": 5,
    "loudness": -8.452,
    "mode": 0,
    "speechiness": 0.0319,
    "acousticness": 0.542,
    "instrumentalness": 0.863,
    "liveness": 0.0949,
    "valence": 0.0403,
    "tempo": 95.024,
    "type": "audio_features",
    "id": "40ka2TBKZf7bPubTAE4xHT",
    "uri": "spotify:track:40ka2TBKZf7bPubTAE4xHT",
    "track_href": "https://api.spotify.com/v1/tracks/40ka2TBKZf7bPubTAE4xHT",
    "analysis_url": "https://api.spotify.com/v1/audio-analysis/40ka2TBKZf7bPubTAE4xHT",
    "duration_ms": 444307,
    "time_signature": 4
}