{
    "danceability": 0.418,
    "energy": 0.718,
    "key": 2,
    "loudness": -7.736,
    "mode": 1,
    "speechiness": 0.556,
    "acousticness": 0.149,
    "instrumentalness": 0,
    "liveness": 0.129,
    "valence": 0.432,
    "tempo": 169.505,
    "type": "audio_features",
    "id": "4adB7Pwq3sPImfVZ4IZ2DR",
    "uri": "spotify:track:4adB7Pwq3sPImfVZ4IZ2DR",
    "track_href": "https://api.spotify.com/v1/tracks/4adB7Pwq3sPImfVZ4IZ2DR",
    "analysis_url": "https://api.spotify.com/v1/audio-analysis/4adB7Pwq3sPImfVZ4IZ2DR",
    "duration_ms": 307043,
    "time_signature": 4
}