{
    "danceability": 0.568,
    "energy": 0.232,
    "key": 10,
    "loudness": -19.811,
    "mode": 1,
    "speechiness": 0.925,
    "acousticness": 0.238,
    "instrumentalness": 0,
    "liveness": 0.384,
    "valence": 0.208,
    "tempo": 213.555,
    "type": "audio_features",
    "id": "4BEYcH1yrugMVVF6BxaN0s",
    "uri": "spotify:track:4BEYcH1yrugMVVF6BxaN0s",
    "track_href": "https://api.spotify.com/v1/tracks/4BEYcH1yrugMVVF6BxaN0s",
    "analysis_url": "https://api.spotify.com/v1/audio-analysis/4BEYcH1yrugMVVF6BxaN0s",
    "duration_ms": 382904,
    "time_signature": 5
}