{
    "danceability": 0.407,
    "energy": 0.246,
    "key": 4,
    "loudness": -15.406,
    "mode": 0,
    "speechiness": 0.0486,
    "acousticness": 0.977,
    "instrumentalness": 3.24e-06,
    "liveness": 0.0636,
    "valence": 0.663,
    "tempo": 76.964,
    "type": "audio_features",
    "id": "4izhEkKwbhd4ITXenkpdob",
    "uri": "spotify:track:4izhEkKwbhd4ITXenkpdob",
    "track_href": "https://api.spotify.com/v1/tracks/4izhEkKwbhd4ITXenkpdob",
    "analysis_url": "https://api.spotify.com/v1/audio-analysis/4izhEkKwbhd4ITXenkpdob",
    "duration_ms": 197027,
    "time_signature": 4
}