{
    "danceability": 0.576,
    "energy": 0.606,
    "key": 7,
    "loudness": -6.352,
    "mode": 1,
    "speechiness": 0.0642,
    "acousticness": 0.46,
    "instrumentalness": 6.5e-06,
    "liveness": 0.111,
    "valence": 0.863,
    "tempo": 88.997,
    "type": "audio_features",
    "id": "4m9USAEG5rPxVve6Ayuznz",
    "uri": "spotify:track:4m9USAEG5rPxVve6Ayuznz",
    "track_href": "https://api.spotify.com/v1/tracks/4m9USAEG5rPxVve6Ayuznz",
    "analysis_url": "https://api.spotify.com/v1/audio-analysis/4m9USAEG5rPxVve6Ayuznz",
    "duration_ms": 159293,
    "time_signature": 4
}