{
    "danceability": 0.498,
    "energy": 0.124,
    "key": 4,
    "loudness": -25.47,
    "mode": 1,
    "speechiness": 0.0601,
    "acousticness": 0.944,
    "instrumentalness": 0.462,
    "liveness": 0.104,
    "valence": 0.394,
    "tempo": 121.749,
    "type": "audio_features",
    "id": "4MozLSat8lL85MTfqpS2RD",
    "uri": "spotify:track:4MozLSat8lL85MTfqpS2RD",
    "track_href": "https://api.spotify.com/v1/tracks/4MozLSat8lL85MTfqpS2RD",
    "analysis_url": "https://api.spotify.com/v1/audio-analysis/4MozLSat8lL85MTfqpS2RD",
    "duration_ms": 116720,
    "time_signature": 4
}