{
    "danceability": 0.271,
    "energy": 0.31,
    "key": 0,
    "loudness": -7.967,
    "mode": 1,
    "speechiness": 0.0309,
    "acousticness": 0.725,
    "instrumentalness": 1.99e-06,
    "liveness": 0.119,
    "valence": 0.16,
    "tempo": 169.614,
    "type": "audio_features",
    "id": "4PxzGOH79jcmmldKgoI9sB",
    "uri": "spotify:track:4PxzGOH79jcmmldKgoI9sB",
    "track_href": "https://api.spotify.com/v1/tracks/4PxzGOH79jcmmldKgoI9sB",
    "analysis_url": "https://api.spotify.com/v1/audio-analysis/4PxzGOH79jcmmldKgoI9sB",
    "duration_ms": 214733,
    "time_signature": 3
}