{
    "danceability": 0.541,
    "energy": 0.437,
    "key": 2,
    "loudness": -11.684,
    "mode": 0,
    "speechiness": 0.0244,
    "acousticness": 0.153,
    "instrumentalness": 0,
    "liveness": 0.096,
    "valence": 0.648,
    "tempo": 91.407,
    "type": "audio_features",
    "id": "4Q4qJYgs4zZ1FFHX2nleB9",
    "uri": "spotify:track:4Q4qJYgs4zZ1FFHX2nleB9",
    "track_href": "https://api.spotify.com/v1/tracks/4Q4qJYgs4zZ1FFHX2nleB9",
    "analysis_url": "https://api.spotify.com/v1/audio-analysis/4Q4qJYgs4zZ1FFHX2nleB9",
    "duration_ms": 220627,
    "time_signature": 4
}