{
    "danceability": 0.358,
    "energy": 0.893,
    "key": 4,
    "loudness": -7.486,
    "mode": 0,
    "speechiness": 0.12,
    "acousticness": 0.0222,
    "instrumentalness": 0.0524,
    "liveness": 0.126,
    "valence": 0.262,
    "tempo": 174.238,
    "type": "audio_features",
    "id": "4ReyTz0y3TGkX48wO3Llot",
    "uri": "spotify:track:4ReyTz0y3TGkX48wO3Llot",
    "track_href": "https://api.spotify.com/v1/tracks/4ReyTz0y3TGkX48wO3Llot",
    "analysis_url": "https://api.spotify.com/v1/audio-analysis/4ReyTz0y3TGkX48wO3Llot",
    "duration_ms": 293653,
    "time_signature": 4
}