{
    "danceability": 0.718,
    "energy": 0.643,
    "key": 7,
    "loudness": -7.482,
    "mode": 1,
    "speechiness": 0.0507,
    "acousticness": 0.642,
    "instrumentalness": 0.00239,
    "liveness": 0.142,
    "valence": 0.486,
    "tempo": 91.949,
    "type": "audio_features",
    "id": "4tHmjVhPeiMhtLyE4JFNdP",
    "uri": "spotify:track:4tHmjVhPeiMhtLyE4JFNdP",
    "track_href": "https://api.spotify.com/v1/tracks/4tHmjVhPeiMhtLyE4JFNdP",
    "analysis_url": "https://api.spotify.com/v1/audio-analysis/4tHmjVhPeiMhtLyE4JFNdP",
    "duration_ms": 181187,
    "time_signature": 4
}