{
    "danceability": 0.46,
    "energy": 0.495,
    "key": 0,
    "loudness": -14.04,
    "mode": 0,
    "speechiness": 0.105,
    "acousticness": 0.102,
    "instrumentalness": 0.912,
    "liveness": 0.111,
    "valence": 0.148,
    "tempo": 164.994,
    "type": "audio_features",
    "id": "4yqlzIc2JpxQceBEJXBNhd",
    "uri": "spotify:track:4yqlzIc2JpxQceBEJXBNhd",
    "track_href": "https://api.spotify.com/v1/tracks/4yqlzIc2JpxQceBEJXBNhd",
    "analysis_url": "https://api.spotify.com/v1/audio-analysis/4yqlzIc2JpxQceBEJXBNhd",
    "duration_ms": 311480,
    "time_signature": 4
}