{
    "danceability": 0.508,
    "energy": 0.964,
    "key": 6,
    "loudness": -3.712,
    "mode": 1,
    "speechiness": 0.0453,
    "acousticness": 5.87e-05,
    "instrumentalness": 3.29e-05,
    "liveness": 0.172,
    "valence": 0.545,
    "tempo": 140.03,
    "type": "audio_features",
    "id": "4YsAIpME2xJ1YERIgmhnzc",
    "uri": "spotify:track:4YsAIpME2xJ1YERIgmhnzc",
    "track_href": "https://api.spotify.com/v1/tracks/4YsAIpME2xJ1YERIgmhnzc",
    "analysis_url": "https://api.spotify.com/v1/audio-analysis/4YsAIpME2xJ1YERIgmhnzc",
    "duration_ms": 200510,
    "time_signature": 4
}