{
    "danceability": 0.478,
    "energy": 0.937,
    "key": 9,
    "loudness": -4.105,
    "mode": 1,
    "speechiness": 0.0412,
    "acousticness": 0.00402,
    "instrumentalness": 0.0179,
    "liveness": 0.0552,
    "valence": 0.5,
    "tempo": 98.998,
    "type": "audio_features",
    "id": "52E9iDkIqHV15tPSpY6lOa",
    "uri": "spotify:track:52E9iDkIqHV15tPSpY6lOa",
    "track_href": "https://api.spotify.com/v1/tracks/52E9iDkIqHV15tPSpY6lOa",
    "analysis_url": "https://api.spotify.com/v1/audio-analysis/52E9iDkIqHV15tPSpY6lOa",
    "duration_ms": 243453,
    "time_signature": 4
}