{
    "danceability": 0.468,
    "energy": 0.348,
    "key": 2,
    "loudness": -13.454,
    "mode": 0,
    "speechiness": 0.0495,
    "acousticness": 0.496,
    "instrumentalness": 0.00113,
    "liveness": 0.117,
    "valence": 0.305,
    "tempo": 127.17,
    "type": "audio_features",
    "id": "52hMydaS1ld25uY0wI1sHW",
    "uri": "spotify:track:52hMydaS1ld25uY0wI1sHW",
    "track_href": "https://api.spotify.com/v1/tracks/52hMydaS1ld25uY0wI1sHW",
    "analysis_url": "https://api.spotify.com/v1/audio-analysis/52hMydaS1ld25uY0wI1sHW",
    "duration_ms": 157600,
    "time_signature": 4
}