{
    "danceability": 0.521,
    "energy": 0.22,
    "key": 9,
    "loudness": -10.202,
    "mode": 1,
    "speechiness": 0.0314,
    "acousticness": 0.647,
    "instrumentalness": 0.00814,
    "liveness": 0.179,
    "valence": 0.135,
    "tempo": 104.03,
    "type": "audio_features",
    "id": "588zNOzyZ0NbK8kMwYv5lO",
    "uri": "spotify:track:588zNOzyZ0NbK8kMwYv5lO",
    "track_href": "https://api.spotify.com/v1/tracks/588zNOzyZ0NbK8kMwYv5lO",
    "analysis_url": "https://api.spotify.com/v1/audio-analysis/588zNOzyZ0NbK8kMwYv5lO",
    "duration_ms": 210507,
    "time_signature": 4
}