{
    "danceability": 0.64,
    "energy": 0.761,
    "key": 2,
    "loudness": -9.053,
    "mode": 1,
    "speechiness": 0.224,
    "acousticness": 0.486,
    "instrumentalness": 0.00696,
    "liveness": 0.452,
    "valence": 0.633,
    "tempo": 111.95,
    "type": "audio_features",
    "id": "5AONQhDlnU6AeCMqUFYCXs",
    "uri": "spotify:track:5AONQhDlnU6AeCMqUFYCXs",
    "track_href": "https://api.spotify.com/v1/tracks/5AONQhDlnU6AeCMqUFYCXs",
    "analysis_url": "https://api.spotify.com/v1/audio-analysis/5AONQhDlnU6AeCMqUFYCXs",
    "duration_ms": 211110,
    "time_signature": 4
}