{
    "danceability": 0.253,
    "energy": 0.129,
    "key": 4,
    "loudness": -26.515,
    "mode": 0,
    "speechiness": 0.049,
    "acousticness": 0.957,
    "instrumentalness": 0.885,
    "liveness": 0.0986,
    "valence": 0.0987,
    "tempo": 79.199,
    "type": "audio_features",
    "id": "5aZrTAdxzSU6dQbU9Wo8DV",
    "uri": "spotify:track:5aZrTAdxzSU6dQbU9Wo8DV",
    "track_href": "https://api.spotify.com/v1/tracks/5aZrTAdxzSU6dQbU9Wo8DV",
    "analysis_url": "https://api.spotify.com/v1/audio-analysis/5aZrTAdxzSU6dQbU9Wo8DV",
    "duration_ms": 299240,
    "time_signature": 4
}