{
    "danceability": 0.12,
    "energy": 0.018,
    "key": 2,
    "loudness": -30.883,
    "mode": 0,
    "speechiness": 0.0357,
    "acousticness": 0.977,
    "instrumentalness": 0.863,
    "liveness": 0.119,
    "valence": 0.0924,
    "tempo": 68.249,
    "type": "audio_features",
    "id": "5CC8QT7TuttcXXSlj5cx2T",
    "uri": "spotify:track:5CC8QT7TuttcXXSlj5cx2T",
    "track_href": "https://api.spotify.com/v1/tracks/5CC8QT7TuttcXXSlj5cx2T",
    "analysis_url": "https://api.spotify.com/v1/audio-analysis/5CC8QT7TuttcXXSlj5cx2T",
    "duration_ms": 191000,
    "time_signature": 4
}