{
    "danceability": 0.716,
    "energy": 0.593,
    "key": 11,
    "loudness": -11.89,
    "mode": 0,
    "speechiness": 0.083,
    "acousticness": 0.151,
    "instrumentalness": 0.495,
    "liveness": 0.235,
    "valence": 0.151,
    "tempo": 120.03,
    "type": "audio_features",
    "id": "5dRirPtSxSqG1lBlX3L6im",
    "uri": "spotify:track:5dRirPtSxSqG1lBlX3L6im",
    "track_href": "https://api.spotify.com/v1/tracks/5dRirPtSxSqG1lBlX3L6im",
    "analysis_url": "https://api.spotify.com/v1/audio-analysis/5dRirPtSxSqG1lBlX3L6im",
    "duration_ms": 214200,
    "time_signature": 4
}