{
    "danceability": 0.756,
    "energy": 0.73,
    "key": 9,
    "loudness": -7.833,
    "mode": 1,
    "speechiness": 0.0706,
    "acousticness": 0.133,
    "instrumentalness": 1.01e-06,
    "liveness": 0.331,
    "valence": 0.65,
    "tempo": 104.966,
    "type": "audio_features",
    "id": "5E4fq3FNmrqj9pQlD4zbrt",
    "uri": "spotify:track:5E4fq3FNmrqj9pQlD4zbrt",
    "track_href": "https://api.spotify.com/v1/tracks/5E4fq3FNmrqj9pQlD4zbrt",
    "analysis_url": "https://api.spotify.com/v1/audio-analysis/5E4fq3FNmrqj9pQlD4zbrt",
    "duration_ms": 205733,
    "time_signature": 4
}