{
    "danceability": 0.558,
    "energy": 0.8,
    "key": 3,
    "loudness": -3.027,
    "mode": 1,
    "speechiness": 0.0718,
    "acousticness": 0.00871,
    "instrumentalness": 0.443,
    "liveness": 0.12,
    "valence": 0.491,
    "tempo": 174.031,
    "type": "audio_features",
    "id": "5FsKpHT0BaWSCuvmwUCZ6J",
    "uri": "spotify:track:5FsKpHT0BaWSCuvmwUCZ6J",
    "track_href": "https://api.spotify.com/v1/tracks/5FsKpHT0BaWSCuvmwUCZ6J",
    "analysis_url": "https://api.spotify.com/v1/audio-analysis/5FsKpHT0BaWSCuvmwUCZ6J",
    "duration_ms": 226509,
    "time_signature": 4
}