{
    "danceability": 0.542,
    "energy": 0.747,
    "key": 11,
    "loudness": -4.143,
    "mode": 0,
    "speechiness": 0.0291,
    "acousticness": 0.126,
    "instrumentalness": 9.8e-05,
    "liveness": 0.331,
    "valence": 0.481,
    "tempo": 91.038,
    "type": "audio_features",
    "id": "5I2OjdgZWSkY4Cbsle3K4g",
    "uri": "spotify:track:5I2OjdgZWSkY4Cbsle3K4g",
    "track_href": "https://api.spotify.com/v1/tracks/5I2OjdgZWSkY4Cbsle3K4g",
    "analysis_url": "https://api.spotify.com/v1/audio-analysis/5I2OjdgZWSkY4Cbsle3K4g",
    "duration_ms": 246880,
    "time_signature": 4
}