{
    "danceability": 0.365,
    "energy": 0.487,
    "key": 9,
    "loudness": -6.523,
    "mode": 1,
    "speechiness": 0.0374,
    "acousticness": 0.204,
    "instrumentalness": 0,
    "liveness": 0.0934,
    "valence": 0.474,
    "tempo": 207.881,
    "type": "audio_features",
    "id": "5jI9fVQ1QqUygoNpVRdzu3",
    "uri": "spotify:track:5jI9fVQ1QqUygoNpVRdzu3",
    "track_href": "https://api.spotify.com/v1/tracks/5jI9fVQ1QqUygoNpVRdzu3",
    "analysis_url": "https://api.spotify.com/v1/audio-analysis/5jI9fVQ1QqUygoNpVRdzu3",
    "duration_ms": 210161,
    "time_signature": 3
}