{
    "danceability": 0.875,
    "energy": 0.394,
    "key": 11,
    "loudness": -9.552,
    "mode": 1,
    "speechiness": 0.042,
    "acousticness": 0.545,
    "instrumentalness": 0.000358,
    "liveness": 0.114,
    "valence": 0.193,
    "tempo": 123.655,
    "type": "audio_features",
    "id": "5lt2cMmHxKMpc0LsWzTyGw",
    "uri": "spotify:track:5lt2cMmHxKMpc0LsWzTyGw",
    "track_href": "https://api.spotify.com/v1/tracks/5lt2cMmHxKMpc0LsWzTyGw",
    "analysis_url": "https://api.spotify.com/v1/audio-analysis/5lt2cMmHxKMpc0LsWzTyGw",
    "duration_ms": 197213,
    "time_signature": 4
}