{
    "danceability": 0.602,
    "energy": 0.12,
    "key": 10,
    "loudness": -15.26,
    "mode": 0,
    "speechiness": 0.493,
    "acousticness": 0.0146,
    "instrumentalness": 0,
    "liveness": 0.121,
    "valence": 0.293,
    "tempo": 191.664,
    "type": "audio_features",
    "id": "5m3FNrT4sNazo021n4QMBU",
    "uri": "spotify:track:5m3FNrT4sNazo021n4QMBU",
    "track_href": "https://api.spotify.com/v1/tracks/5m3FNrT4sNazo021n4QMBU",
    "analysis_url": "https://api.spotify.com/v1/audio-analysis/5m3FNrT4sNazo021n4QMBU",
    "duration_ms": 37933,
    "time_signature": 5
}