{
    "danceability": 0.674,
    "energy": 0.398,
    "key": 9,
    "loudness": -8.963,
    "mode": 0,
    "speechiness": 0.0273,
    "acousticness": 0.0267,
    "instrumentalness": 2.81e-06,
    "liveness": 0.092,
    "valence": 0.317,
    "tempo": 100.044,
    "type": "audio_features",
    "id": "5MZAFtKcOWfmUp60mf8veU",
    "uri": "spotify:track:5MZAFtKcOWfmUp60mf8veU",
    "track_href": "https://api.spotify.com/v1/tracks/5MZAFtKcOWfmUp60mf8veU",
    "analysis_url": "https://api.spotify.com/v1/audio-analysis/5MZAFtKcOWfmUp60mf8veU",
    "duration_ms": 241213,
    "time_signature": 4
}