{
    "danceability": 0.677,
    "energy": 0.744,
    "key": 10,
    "loudness": -6.806,
    "mode": 0,
    "speechiness": 0.0295,
    "acousticness": 0.0404,
    "instrumentalness": 0.00016,
    "liveness": 0.074,
    "valence": 0.631,
    "tempo": 124.08,
    "type": "audio_features",
    "id": "5p1ex0pXv6jSPJ6QbumQpD",
    "uri": "spotify:track:5p1ex0pXv6jSPJ6QbumQpD",
    "track_href": "https://api.spotify.com/v1/tracks/5p1ex0pXv6jSPJ6QbumQpD",
    "analysis_url": "https://api.spotify.com/v1/audio-analysis/5p1ex0pXv6jSPJ6QbumQpD",
    "duration_ms": 152913,
    "time_signature": 4
}