{
    "danceability": 0.183,
    "energy": 0.149,
    "key": 0,
    "loudness": -20.798,
    "mode": 1,
    "speechiness": 0.0325,
    "acousticness": 0.151,
    "instrumentalness": 0.0346,
    "liveness": 0.245,
    "valence": 0.058,
    "tempo": 96.711,
    "type": "audio_features",
    "id": "5Swnw3xi06SkYEz7bF559s",
    "uri": "spotify:track:5Swnw3xi06SkYEz7bF559s",
    "track_href": "https://api.spotify.com/v1/tracks/5Swnw3xi06SkYEz7bF559s",
    "analysis_url": "https://api.spotify.com/v1/audio-analysis/5Swnw3xi06SkYEz7bF559s",
    "duration_ms": 266387,
    "time_signature": 4
}