{
    "danceability": 0.568,
    "energy": 0.891,
    "key": 0,
    "loudness": -5.786,
    "mode": 1,
    "speechiness": 0.0376,
    "acousticness": 0.000896,
    "instrumentalness": 0.000137,
    "liveness": 0.357,
    "valence": 0.522,
    "tempo": 104.954,
    "type": "audio_features",
    "id": "5TUZhrb8UaaA76NhzZax2Z",
    "uri": "spotify:track:5TUZhrb8UaaA76NhzZax2Z",
    "track_href": "https://api.spotify.com/v1/tracks/5TUZhrb8UaaA76NhzZax2Z",
    "analysis_url": "https://api.spotify.com/v1/audio-analysis/5TUZhrb8UaaA76NhzZax2Z",
    "duration_ms": 190227,
    "time_signature": 4
}