{
    "danceability": 0.559,
    "energy": 0.815,
    "key": 9,
    "loudness": -6.325,
    "mode": 0,
    "speechiness": 0.0445,
    "acousticness": 0.00363,
    "instrumentalness": 0.0719,
    "liveness": 0.668,
    "valence": 0.209,
    "tempo": 128.001,
    "type": "audio_features",
    "id": "5vQIaNoKsT4xkG1j2KFBFs",
    "uri": "spotify:track:5vQIaNoKsT4xkG1j2KFBFs",
    "track_href": "https://api.spotify.com/v1/tracks/5vQIaNoKsT4xkG1j2KFBFs",
    "analysis_url": "https://api.spotify.com/v1/audio-analysis/5vQIaNoKsT4xkG1j2KFBFs",
    "duration_ms": 328213,
    "time_signature": 4
}