{
    "danceability": 0.561,
    "energy": 0.383,
    "key": 9,
    "loudness": -14.322,
    "mode": 1,
    "speechiness": 0.0859,
    "acousticness": 0.97,
    "instrumentalness": 0.0132,
    "liveness": 0.264,
    "valence": 0.537,
    "tempo": 113.159,
    "type": "audio_features",
    "id": "5Wv2CIRajNnmUDeZJgwR4s",
    "uri": "spotify:track:5Wv2CIRajNnmUDeZJgwR4s",
    "track_href": "https://api.spotify.com/v1/tracks/5Wv2CIRajNnmUDeZJgwR4s",
    "analysis_url": "https://api.spotify.com/v1/audio-analysis/5Wv2CIRajNnmUDeZJgwR4s",
    "duration_ms": 305493,
    "time_signature": 4
}