{
    "danceability": 0.631,
    "energy": 0.284,
    "key": 6,
    "loudness": -16.532,
    "mode": 1,
    "speechiness": 0.607,
    "acousticness": 0.886,
    "instrumentalness": 0,
    "liveness": 0.177,
    "valence": 0.418,
    "tempo": 129.505,
    "type": "audio_features",
    "id": "5zZVZ6nP9LLokai06eZpvF",
    "uri": "spotify:track:5zZVZ6nP9LLokai06eZpvF",
    "track_href": "https://api.spotify.com/v1/tracks/5zZVZ6nP9LLokai06eZpvF",
    "analysis_url": "https://api.spotify.com/v1/audio-analysis/5zZVZ6nP9LLokai06eZpvF",
    "duration_ms": 175067,
    "time_signature": 1
}