{
    "danceability": 0.38,
    "energy": 0.333,
    "key": 9,
    "loudness": -11.507,
    "mode": 1,
    "speechiness": 0.0284,
    "acousticness": 0.8,
    "instrumentalness": 0.891,
    "liveness": 0.134,
    "valence": 0.358,
    "tempo": 79.891,
    "type": "audio_features",
    "id": "6A6ELFKSmU4Sgnfem0SyRd",
    "uri": "spotify:track:6A6ELFKSmU4Sgnfem0SyRd",
    "track_href": "https://api.spotify.com/v1/tracks/6A6ELFKSmU4Sgnfem0SyRd",
    "analysis_url": "https://api.spotify.com/v1/audio-analysis/6A6ELFKSmU4Sgnfem0SyRd",
    "duration_ms": 210040,
    "time_signature": 3
}