{
    "danceability": 0.641,
    "energy": 0.648,
    "key": 6,
    "loudness": -5.318,
    "mode": 1,
    "speechiness": 0.0418,
    "acousticness": 0.0159,
    "instrumentalness": 0.000329,
    "liveness": 0.413,
    "valence": 0.373,
    "tempo": 132.983,
    "type": "audio_features",
    "id": "6C3KjmM03L3CKHf2vhU5Pa",
    "uri": "spotify:track:6C3KjmM03L3CKHf2vhU5Pa",
    "track_href": "https://api.spotify.com/v1/tracks/6C3KjmM03L3CKHf2vhU5Pa",
    "analysis_url": "https://api.spotify.com/v1/audio-analysis/6C3KjmM03L3CKHf2vhU5Pa",
    "duration_ms": 175843,
    "time_signature": 4
}