{
    "danceability": 0.595,
    "energy": 0.941,
    "key": 8,
    "loudness": -3.756,
    "mode": 1,
    "speechiness": 0.124,
    "acousticness": 0.0315,
    "instrumentalness": 0.0156,
    "liveness": 0.114,
    "valence": 0.598,
    "tempo": 151.936,
    "type": "audio_features",
    "id": "6cS2reOYomC1kVSeNR9Isp",
    "uri": "spotify:track:6cS2reOYomC1kVSeNR9Isp",
    "track_href": "https://api.spotify.com/v1/tracks/6cS2reOYomC1kVSeNR9Isp",
    "analysis_url": "https://api.spotify.com/v1/audio-analysis/6cS2reOYomC1kVSeNR9Isp",
    "duration_ms": 246280,
    "time_signature": 4
}