{
    "danceability": 0.713,
    "energy": 0.113,
    "key": 8,
    "loudness": -17.947,
    "mode": 0,
    "speechiness": 0.554,
    "acousticness": 0.525,
    "instrumentalness": 0,
    "liveness": 0.116,
    "valence": 0.252,
    "tempo": 125.209,
    "type": "audio_features",
    "id": "6FbBHLHw1KHbIDfrVpvlgp",
    "uri": "spotify:track:6FbBHLHw1KHbIDfrVpvlgp",
    "track_href": "https://api.spotify.com/v1/tracks/6FbBHLHw1KHbIDfrVpvlgp",
    "analysis_url": "https://api.spotify.com/v1/audio-analysis/6FbBHLHw1KHbIDfrVpvlgp",
    "duration_ms": 1344213,
    "time_signature": 5
}