{
    "danceability": 0.477,
    "energy": 0.426,
    "key": 6,
    "loudness": -6.961,
    "mode": 1,
    "speechiness": 0.043,
    "acousticness": 0.544,
    "instrumentalness": 0,
    "liveness": 0.0903,
    "valence": 0.789,
    "tempo": 184.866,
    "type": "audio_features",
    "id": "6GrrkiCRO3HYdgRpO4eKEL",
    "uri": "spotify:track:6GrrkiCRO3HYdgRpO4eKEL",
    "track_href": "https://api.spotify.com/v1/tracks/6GrrkiCRO3HYdgRpO4eKEL",
    "analysis_url": "https://api.spotify.com/v1/audio-analysis/6GrrkiCRO3HYdgRpO4eKEL",
    "duration_ms": 200067,
    "time_signature": 3
}