{
    "danceability": 0.651,
    "energy": 0.728,
    "key": 9,
    "loudness": -13.385,
    "mode": 1,
    "speechiness": 0.937,
    "acousticness": 0.847,
    "instrumentalness": 0,
    "liveness": 0.946,
    "valence": 0.774,
    "tempo": 140.053,
    "type": "audio_features",
    "id": "6MGFa8V2izUNNINTJXHiqQ",
    "uri": "spotify:track:6MGFa8V2izUNNINTJXHiqQ",
    "track_href": "https://api.spotify.com/v1/tracks/6MGFa8V2izUNNINTJXHiqQ",
    "analysis_url": "https://api.spotify.com/v1/audio-analysis/6MGFa8V2izUNNINTJXHiqQ",
    "duration_ms": 162760,
    "time_signature": 4
}