{
    "danceability": 0.675,
    "energy": 0.601,
    "key": 11,
    "loudness": -4.733,
    "mode": 0,
    "speechiness": 0.116,
    "acousticness": 0.00372,
    "instrumentalness": 0,
    "liveness": 0.0458,
    "valence": 0.931,
    "tempo": 127.938,
    "type": "audio_features",
    "id": "6qUSs4FDzZUdAhY6JDIJfa",
    "uri": "spotify:track:6qUSs4FDzZUdAhY6JDIJfa",
    "track_href": "https://api.spotify.com/v1/tracks/6qUSs4FDzZUdAhY6JDIJfa",
    "analysis_url": "https://api.spotify.com/v1/audio-analysis/6qUSs4FDzZUdAhY6JDIJfa",
    "duration_ms": 201040,
    "time_signature": 4
}