{
    "danceability": 0.685,
    "energy": 0.445,
    "key": 7,
    "loudness": -16.504,
    "mode": 1,
    "speechiness": 0.0935,
    "acousticness": 0.335,
    "instrumentalness": 0.00275,
    "liveness": 0.182,
    "valence": 0.272,
    "tempo": 107.986,
    "type": "audio_features",
    "id": "6TZ4CR2pyh7Tstz9fYBYCq",
    "uri": "spotify:track:6TZ4CR2pyh7Tstz9fYBYCq",
    "track_href": "https://api.spotify.com/v1/tracks/6TZ4CR2pyh7Tstz9fYBYCq",
    "analysis_url": "https://api.spotify.com/v1/audio-analysis/6TZ4CR2pyh7Tstz9fYBYCq",
    "duration_ms": 463413,
    "time_signature": 4
}