{
    "danceability": 0.655,
    "energy": 0.666,
    "key": 5,
    "loudness": -5.309,
    "mode": 1,
    "speechiness": 0.0612,
    "acousticness": 0.134,
    "instrumentalness": 2.12e-05,
    "liveness": 0.0683,
    "valence": 0.272,
    "tempo": 102.977,
    "type": "audio_features",
    "id": "75NhhYjHO43mvZgYtnXgti",
    "uri": "spotify:track:75NhhYjHO43mvZgYtnXgti",
    "track_href": "https://api.spotify.com/v1/tracks/75NhhYjHO43mvZgYtnXgti",
    "analysis_url": "https://api.spotify.com/v1/audio-analysis/75NhhYjHO43mvZgYtnXgti",
    "duration_ms": 181812,
    "time_signature": 4
}