{
    "danceability": 0.184,
    "energy": 0.0507,
    "key": 1,
    "loudness": -26.721,
    "mode": 1,
    "speechiness": 0.0474,
    "acousticness": 0.989,
    "instrumentalness": 0.928,
    "liveness": 0.0444,
    "valence": 0.0366,
    "tempo": 50.917,
    "type": "audio_features",
    "id": "7ACLQLZ1I7PbyKTS4E9whS",
    "uri": "spotify:track:7ACLQLZ1I7PbyKTS4E9whS",
    "track_href": "https://api.spotify.com/v1/tracks/7ACLQLZ1I7PbyKTS4E9whS",
    "analysis_url": "https://api.spotify.com/v1/audio-analysis/7ACLQLZ1I7PbyKTS4E9whS",
    "duration_ms": 626533,
    "time_signature": 4
}