{
    "danceability": 0.797,
    "energy": 0.533,
    "key": 0,
    "loudness": -9.74,
    "mode": 0,
    "speechiness": 0.0412,
    "acousticness": 0.0172,
    "instrumentalness": 0.000152,
    "liveness": 0.103,
    "valence": 0.329,
    "tempo": 131.036,
    "type": "audio_features",
    "id": "7AQim7LbvFVZJE3O8TYgf2",
    "uri": "spotify:track:7AQim7LbvFVZJE3O8TYgf2",
    "track_href": "https://api.spotify.com/v1/tracks/7AQim7LbvFVZJE3O8TYgf2",
    "analysis_url": "https://api.spotify.com/v1/audio-analysis/7AQim7LbvFVZJE3O8TYgf2",
    "duration_ms": 146520,
    "time_signature": 4
}