{
    "danceability": 0.652,
    "energy": 0.763,
    "key": 0,
    "loudness": -5.807,
    "mode": 1,
    "speechiness": 0.0323,
    "acousticness": 0.112,
    "instrumentalness": 0,
    "liveness": 0.281,
    "valence": 0.278,
    "tempo": 123.012,
    "type": "audio_features",
    "id": "7B0cmoe2K9vOTaYZP8AWP8",
    "uri": "spotify:track:7B0cmoe2K9vOTaYZP8AWP8",
    "track_href": "https://api.spotify.com/v1/tracks/7B0cmoe2K9vOTaYZP8AWP8",
    "analysis_url": "https://api.spotify.com/v1/audio-analysis/7B0cmoe2K9vOTaYZP8AWP8",
    "duration_ms": 199120,
    "time_signature": 4
}