{
    "danceability": 0.801,
    "energy": 0.573,
    "key": 8,
    "loudness": -9.893,
    "mode": 1,
    "speechiness": 0.0688,
    "acousticness": 0.731,
    "instrumentalness": 0.962,
    "liveness": 0.111,
    "valence": 0.887,
    "tempo": 167.937,
    "type": "audio_features",
    "id": "7EzgzkG9PfgzVMrXJKurS3",
    "uri": "spotify:track:7EzgzkG9PfgzVMrXJKurS3",
    "track_href": "https://api.spotify.com/v1/tracks/7EzgzkG9PfgzVMrXJKurS3",
    "analysis_url": "https://api.spotify.com/v1/audio-analysis/7EzgzkG9PfgzVMrXJKurS3",
    "duration_ms": 197143,
    "time_signature": 4
}