{
    "danceability": 0.342,
    "energy": 0.723,
    "key": 9,
    "loudness": -8.0,
    "mode": 1,
    "speechiness": 0.0517,
    "acousticness": 0.00666,
    "instrumentalness": 0.13,
    "liveness": 0.157,
    "valence": 0.59,
    "tempo": 83.433,
    "type": "audio_features",
    "id": "7pzVqCZdYKM7oEPwaiQchB",
    "uri": "spotify:track:7pzVqCZdYKM7oEPwaiQchB",
    "track_href": "https://api.spotify.com/v1/tracks/7pzVqCZdYKM7oEPwaiQchB",
    "analysis_url": "https://api.spotify.com/v1/audio-analysis/7pzVqCZdYKM7oEPwaiQchB",
    "duration_ms": 298280,
    "time_signature": 4
}